gllm/_C.abi3.so
gllm/__init__.py
gllm/_custom_ops.py
gllm/_moe_C.abi3.so
gllm/async_llm_engine.py
gllm/async_worker.py
gllm/dist_utils.py
gllm/frontend_scheduler.py
gllm/id_allocator.py
gllm/input_data.py
gllm/llm_engine.py
gllm/memory_manager.py
gllm/model_loader.py
gllm/model_runner.py
gllm/sequence.py
gllm/utils.py
gllm/worker.py
gllm/worker_scheduler.py
gllm/zmq_comm.py
gllm/entrypoints/api_server.py
gllm/entrypoints/protocol.py
gllm/entrypoints/serving_chat.py
gllm/entrypoints/serving_completions.py
gllm/layers/activation.py
gllm/layers/attention.py
gllm/layers/layernorm.py
gllm/layers/linear.py
gllm/layers/rotary_embedding.py
gllm/layers/sampler.py
gllm/layers/vocab_parallel_embedding.py
gllm/layers/moe/moe_align_block_size.py
gllm/layers/moe/topk.py
gllm/layers/moe/fused_moe_triton/__init__.py
gllm/layers/moe/fused_moe_triton/fused_moe.py
gllm/layers/moe/fused_moe_triton/layer.py
"gllm/layers/moe/fused_moe_triton/configs/E=1,N=14336,device_name=NVIDIA_A100-SXM4-80GB,dtype=int8_w8a16.json"
"gllm/layers/moe/fused_moe_triton/configs/E=1,N=14336,device_name=NVIDIA_A100-SXM4-80GB.json"
"gllm/layers/moe/fused_moe_triton/configs/E=1,N=1792,device_name=NVIDIA_A100-SXM4-80GB,dtype=int8_w8a16.json"
"gllm/layers/moe/fused_moe_triton/configs/E=1,N=1792,device_name=NVIDIA_A100-SXM4-80GB.json"
"gllm/layers/moe/fused_moe_triton/configs/E=1,N=3072,device_name=NVIDIA_A100-SXM4-80GB,dtype=int8_w8a16.json"
"gllm/layers/moe/fused_moe_triton/configs/E=1,N=3072,device_name=NVIDIA_H100_80GB_HBM3,dtype=int8_w8a16.json"
"gllm/layers/moe/fused_moe_triton/configs/E=1,N=3072,device_name=NVIDIA_H100_80GB_HBM3.json"
"gllm/layers/moe/fused_moe_triton/configs/E=1,N=3584,device_name=NVIDIA_A100-SXM4-80GB,dtype=int8_w8a16.json"
"gllm/layers/moe/fused_moe_triton/configs/E=1,N=3584,device_name=NVIDIA_A100-SXM4-80GB.json"
"gllm/layers/moe/fused_moe_triton/configs/E=1,N=7168,device_name=NVIDIA_A100-SXM4-80GB,dtype=int8_w8a16.json"
gllm_rt-0.0.3.dist-info/licenses/LICENSE
gllm_rt-0.0.3.dist-info/METADATA
gllm_rt-0.0.3.dist-info/WHEEL
gllm_rt-0.0.3.dist-info/top_level.txt
gllm_rt-0.0.3.dist-info/RECORD
