Metadata-Version: 2.4
Name: gllm-rt
Version: 0.0.3
Summary: Global Balanced Pipeline Parallelism System for Distributed LLM Serving with Token Throttling
Author: gLLM Team
License-Expression: Apache-2.0
Classifier: Programming Language :: Python :: 3.9
Classifier: Programming Language :: Python :: 3.10
Classifier: Programming Language :: Python :: 3.11
Classifier: Programming Language :: Python :: 3.12
Classifier: Intended Audience :: Developers
Classifier: Intended Audience :: Information Technology
Classifier: Intended Audience :: Science/Research
Classifier: Topic :: Scientific/Engineering :: Artificial Intelligence
Classifier: Topic :: Scientific/Engineering :: Information Analysis
Requires-Python: >=3.8
License-File: LICENSE
Requires-Dist: pydantic>=2.9
Requires-Dist: numpy<2.0.0
Requires-Dist: cmake>=3.21
Requires-Dist: ninja
Requires-Dist: packaging
Requires-Dist: setuptools>=61
Requires-Dist: wheel
Requires-Dist: tqdm
Requires-Dist: transformers>=4.51.1
Requires-Dist: fastapi<0.113.0,>=0.107.0; python_version < "3.9"
Requires-Dist: fastapi!=0.113.*,!=0.114.0,>=0.107.0; python_version >= "3.9"
Requires-Dist: uvicorn[standard]
Requires-Dist: openai>=1.52.0
Requires-Dist: logger
Requires-Dist: torch==2.5.1
Requires-Dist: zmq
Requires-Dist: aiohttp
Requires-Dist: datasets
Requires-Dist: pillow
Dynamic: license-file
Dynamic: requires-dist
Dynamic: requires-python
